data_processing/__init__.py
data_processing/data_access/__init__.py
data_processing/data_access/arrow_s3.py
data_processing/data_access/data_access.py
data_processing/data_access/data_access_factory.py
data_processing/data_access/data_access_factory_base.py
data_processing/data_access/data_access_local.py
data_processing/data_access/data_access_memory.py
data_processing/data_access/data_access_s3.py
data_processing/data_access/snapshot_utils.py
data_processing/multimodal/__init__.py
data_processing/multimodal/abstract_detector.py
data_processing/multimodal/abstract_transform.py
data_processing/multimodal/util.py
data_processing/runtime/__init__.py
data_processing/runtime/execution_configuration.py
data_processing/runtime/runtime_configuration.py
data_processing/runtime/transform_file_processor.py
data_processing/runtime/transform_launcher.py
data_processing/runtime/pure_python/__init__.py
data_processing/runtime/pure_python/execution_configuration.py
data_processing/runtime/pure_python/runtime_configuration.py
data_processing/runtime/pure_python/transform.py
data_processing/runtime/pure_python/transform_file_processor.py
data_processing/runtime/pure_python/transform_invoker.py
data_processing/runtime/pure_python/transform_launcher.py
data_processing/runtime/pure_python/transform_orchestrator.py
data_processing/runtime/pure_python/transform_runtime.py
data_processing/test_support/__init__.py
data_processing/test_support/abstract_test.py
data_processing/test_support/data_access/__init__.py
data_processing/test_support/data_access/data_access_factory_test.py
data_processing/test_support/launch/__init__.py
data_processing/test_support/launch/transform_test.py
data_processing/test_support/transform/__init__.py
data_processing/test_support/transform/binary_transform_test.py
data_processing/test_support/transform/noop_folder_transform.py
data_processing/test_support/transform/noop_transform.py
data_processing/test_support/transform/table_transform_test.py
data_prep_toolkit-1.1.6.dist-info/METADATA
data_prep_toolkit-1.1.6.dist-info/WHEEL
data_prep_toolkit-1.1.6.dist-info/top_level.txt
data_prep_toolkit-1.1.6.dist-info/RECORD
