Metadata-Version: 2.4
Name: data_prep_toolkit
Version: 1.1.6
Summary: Data Preparation Toolkit Library for Ray and Python
Author-email: Maroun Touma <touma@us.ibm.com>
License: Apache-2.0
Keywords: data,data preprocessing,data preparation,llm,generative,ai,fine-tuning,llmapps
Requires-Python: <3.13,>=3.10
Requires-Dist: numpy<2.0.0
Requires-Dist: pyarrow<=17.0.0
Requires-Dist: boto3<=1.38.18
Requires-Dist: mmh3
Requires-Dist: psutil
Requires-Dist: polars>=1.9.0
Requires-Dist: transformers
Requires-Dist: fasttext-wheel
Requires-Dist: huggingface-hub<1.0.0,>=0.21.4
Requires-Dist: python-json-logger
Provides-Extra: dev
Requires-Dist: twine; extra == "dev"
Requires-Dist: pytest>=7.3.2; extra == "dev"
Requires-Dist: pytest-dotenv>=0.5.2; extra == "dev"
Requires-Dist: pytest-env>=1.0.0; extra == "dev"
Requires-Dist: pre-commit>=3.3.2; extra == "dev"
Requires-Dist: pytest-cov>=4.1.0; extra == "dev"
Requires-Dist: pytest-mock>=3.10.0; extra == "dev"
Requires-Dist: moto==5.0.5; extra == "dev"
Requires-Dist: markupsafe==2.0.1; extra == "dev"
Provides-Extra: ray
Requires-Dist: ray[default]==2.36.1; extra == "ray"
Requires-Dist: fastapi>=0.110.2; extra == "ray"
Requires-Dist: pillow>=10.3.0; extra == "ray"
Provides-Extra: spark
Requires-Dist: pyspark<=3.5.5,>=3.5.2; extra == "spark"
Requires-Dist: psutil>=6.0.0; extra == "spark"
Requires-Dist: PyYAML>=6.0.2; extra == "spark"
